PyTasky/__init__.py
PyTasky/client.py
PyTasky/errors/__init__.py
PyTasky/errors/accounts.py
PyTasky/errors/api_limits.py
PyTasky/errors/groups.py
PyTasky/errors/types.py
PyTasky/errors/users.py
PyTasky/types/__init__.py
PyTasky/types/groups.py
PyTasky/types/users.py
PyTasky-1.2.0.dist-info/LICENSE
PyTasky-1.2.0.dist-info/METADATA
PyTasky-1.2.0.dist-info/WHEEL
PyTasky-1.2.0.dist-info/top_level.txt
PyTasky-1.2.0.dist-info/RECORD
