Metadata-Version: 2.1
Name: PyTasky
Version: 1.2.0
Summary: Task System api for python
Home-page: https://github.com/immmdreza/PyTasky
Author: immmdreza
Author-email: ir310022@gmail.com
License: UNKNOWN
Platform: UNKNOWN
Classifier: Programming Language :: Python :: 3
Classifier: License :: OSI Approved :: MIT License
Classifier: Operating System :: OS Independent
Requires-Python: >=3.6
